README.md
setup.py
cwl_airflow_tester/__init__.py
cwl_airflow_tester/main.py
cwl_airflow_tester.egg-info/PKG-INFO
cwl_airflow_tester.egg-info/SOURCES.txt
cwl_airflow_tester.egg-info/dependency_links.txt
cwl_airflow_tester.egg-info/entry_points.txt
cwl_airflow_tester.egg-info/not-zip-safe
cwl_airflow_tester.egg-info/requires.txt
cwl_airflow_tester.egg-info/top_level.txt
cwl_airflow_tester/utils/__init__.py
cwl_airflow_tester/utils/airflow.py
cwl_airflow_tester/utils/checker.py
cwl_airflow_tester/utils/cwl.py
cwl_airflow_tester/utils/helpers.py
cwl_airflow_tester/utils/logger.py
cwl_airflow_tester/utils/mute.py
cwl_airflow_tester/utils/spinner.py